cyclic_crop_rotation/__init__.py
cyclic_crop_rotation/rotation.py
cyclic_crop_rotation/seq_generate.py
cyclic_crop_rotation/seq_property.py
cyclic_crop_rotation/token.py
cyclic_crop_rotation/window.py
cyclic_crop_rotation-2025.0.1.dist-info/METADATA
cyclic_crop_rotation-2025.0.1.dist-info/WHEEL
cyclic_crop_rotation-2025.0.1.dist-info/licenses/LICENSE
cyclic_crop_rotation-2025.0.1.dist-info/RECORD
