Metadata-Version: 2.4
Name: cyclic_crop_rotation
Version: 2025.0.1
Summary: Cyclic crop rotations labeling for crop sequences
Project-URL: Homepage, https://github.com/hsizek/cyclic-crop-rotation
Project-URL: Issues, https://github.com/hsizek/cyclic-crop-rotation/issues
Author-email: Herbert Sizek <sizek.herbert@gmail.com>
Maintainer-email: Herbert Sizek <sizek.herbert@gmail.com>
License-Expression: MIT
License-File: LICENSE
Keywords: crop rotation,crop sequence,crop transition,cyclic rotation
Classifier: Operating System :: OS Independent
Classifier: Programming Language :: Python :: 3
Requires-Python: >=3.8
